ppe/__init__.py
ppe/manage.py
ppe/version.py
ppe/config/__init__.py
ppe/config/global_config.py
ppe/database_util/__init__.py
ppe/database_util/db.py
ppe/factory/__init__.py
ppe/factory/app_factory.py
ppe/helper/__init__.py
ppe/helper/helper.py
ppe/routes/__init__.py
ppe/routes/routes.py
ppeservice-0.0.3.0.dist-info/METADATA
ppeservice-0.0.3.0.dist-info/WHEEL
ppeservice-0.0.3.0.dist-info/entry_points.txt
ppeservice-0.0.3.0.dist-info/top_level.txt
ppeservice-0.0.3.0.dist-info/RECORD
