Metadata-Version: 2.1
Name: ppeservice
Version: 0.0.3.0
Summary: Personal website generator(could be any website or small services generator)
Home-page: https://github.com/JunqiZhang0/py-production-experiment
Author: Ye Zhang, Junqi Zhang
Author-email: zhangforchat@gmail.com
License: GPLv3
Platform: UNKNOWN
Classifier: Development Status :: 1 - Planning
Requires-Dist: alembic (==1.4.2)
Requires-Dist: aniso8601 (==8.0.0)
Requires-Dist: attrs (==19.3.0)
Requires-Dist: autopep8 (==1.5.3)
Requires-Dist: cffi (==1.14.0)
Requires-Dist: click (==7.1.2)
Requires-Dist: cryptography (==2.9.2)
Requires-Dist: Flask (==1.1.2)
Requires-Dist: Flask-HTTPAuth (==4.1.0)
Requires-Dist: Flask-Migrate (==2.5.3)
Requires-Dist: flask-restx (==0.2.0)
Requires-Dist: Flask-Script (==2.0.6)
Requires-Dist: Flask-SQLAlchemy (==2.4.3)
Requires-Dist: flask-swagger-ui (==3.25.0)
Requires-Dist: importlib-metadata (==1.6.1)
Requires-Dist: itsdangerous (==1.1.0)
Requires-Dist: Jinja2 (==2.11.2)
Requires-Dist: jsonschema (==3.2.0)
Requires-Dist: Mako (==1.1.3)
Requires-Dist: MarkupSafe (==1.1.1)
Requires-Dist: marshmallow (==3.6.1)
Requires-Dist: marshmallow-sqlalchemy (==0.23.1)
Requires-Dist: pycodestyle (==2.6.0)
Requires-Dist: pycparser (==2.20)
Requires-Dist: PyJWT (==1.7.1)
Requires-Dist: PyMySQL (==0.9.3)
Requires-Dist: pyrsistent (==0.16.0)
Requires-Dist: python-dateutil (==2.8.1)
Requires-Dist: python-editor (==1.0.4)
Requires-Dist: pytz (==2020.1)
Requires-Dist: six (==1.15.0)
Requires-Dist: SQLAlchemy (==1.3.17)
Requires-Dist: toml (==0.10.1)
Requires-Dist: Werkzeug (==1.0.1)
Requires-Dist: zipp (==3.1.0)
